README.md
setup.cfg
setup.py
top_drawer/__init__.py
top_drawer/_args.py
top_drawer/_cli.py
top_drawer/_config.py
top_drawer/_thesaurus.py
top_drawer/_validations.py
top_drawer/_version.py
top_drawer.egg-info/PKG-INFO
top_drawer.egg-info/SOURCES.txt
top_drawer.egg-info/dependency_links.txt
top_drawer.egg-info/entry_points.txt
top_drawer.egg-info/requires.txt
top_drawer.egg-info/top_level.txt