Metadata-Version: 2.1
Name: top-drawer
Version: 0.1.0
Summary: Package name chooser
Home-page: UNKNOWN
Author: Philippe Duval
Author-email: t4rk@outlook.com
License: MIT
Keywords: choice,chooser,name
Platform: UNKNOWN
